sopaper/__init__.py
sopaper/__main__.py
sopaper/authorfetch.py
sopaper/contentsearch.py
sopaper/dbsearch.py
sopaper/job.py
sopaper/pdfprocess.py
sopaper/queryhandler.py
sopaper/test-fetcher.py
sopaper/test-searcher.py
sopaper/ukconfig.py
sopaper/ukdbconn.py
sopaper/uklogger.py
sopaper/fetcher/__init__.py
sopaper/fetcher/arxiv.py
sopaper/fetcher/base.py
sopaper/fetcher/direct.py
sopaper/fetcher/dlacm.py
sopaper/fetcher/ieee.py
sopaper/fetcher/sciencedirect.py
sopaper/lib/__init__.py
sopaper/lib/abbr.dic
sopaper/lib/downloader.py
sopaper/lib/exc.py
sopaper/lib/mailutil.py
sopaper/lib/pdf2html.py
sopaper/lib/pdfutil.py
sopaper/lib/singleton.py
sopaper/lib/textutil.py
sopaper/lib/timeout.py
sopaper/lib/ukutil.py
sopaper/searcher/__init__.py
sopaper/searcher/google.py
sopaper/searcher/gscholar.py
sopaper/xpengine/__init__.py
sopaper/xpengine/indexer.py
sopaper/xpengine/run-xp.py
sopaper/xpengine/searcher.py
sopaper/xpengine/xpcommon.py
sopaper-0.8.dist-info/DESCRIPTION.rst
sopaper-0.8.dist-info/METADATA
sopaper-0.8.dist-info/RECORD
sopaper-0.8.dist-info/WHEEL
sopaper-0.8.dist-info/entry_points.txt
sopaper-0.8.dist-info/metadata.json
sopaper-0.8.dist-info/top_level.txt
