Metadata-Version: 2.0
Name: sopaper
Version: 0.8
Summary: Automatically search and download paper
Home-page: https://github.com/ppwwyyxx/sopaper
Author: Yuxin Wu
Author-email: ppwwyyxxc@gmail.com
License: UNKNOWN
Keywords: Utility
Platform: UNKNOWN
Requires-Dist: beautifulsoup4
Requires-Dist: requests
Requires-Dist: termcolor
